SharedResources/__init__.py
SharedResources/_shared_resources.py
SharedResources/_version.py
rf_shared_resources-0.1.2.dist-info/LICENSE
rf_shared_resources-0.1.2.dist-info/METADATA
rf_shared_resources-0.1.2.dist-info/WHEEL
rf_shared_resources-0.1.2.dist-info/top_level.txt
rf_shared_resources-0.1.2.dist-info/RECORD
