Metadata-Version: 2.1
Name: rf-shared-resources
Version: 0.1.2
Summary: Utility to share Robot Framework resource files in Python packages.
Home-page: https://github.com/kangasta/rf-shared-resources
Author: Toni Kangas
Classifier: Programming Language :: Python :: 3
Classifier: License :: OSI Approved :: MIT License
Classifier: Operating System :: OS Independent
Requires-Python: >=3.6
License-File: LICENSE
Requires-Dist: robotframework-pythonlibcore
Requires-Dist: importlib-resources ; python_version < "3.7"
